setup.cfg
setup.py
zhdan_utils/__init__.py
zhdan_utils/default_args.py
zhdan_utils/timer.py
zhdan_utils.egg-info/PKG-INFO
zhdan_utils.egg-info/SOURCES.txt
zhdan_utils.egg-info/dependency_links.txt
zhdan_utils.egg-info/not-zip-safe
zhdan_utils.egg-info/top_level.txt
zhdan_utils/opencl/__init__.py
zhdan_utils/opencl/opencl_shader_run.py