Metadata-Version: 2.1
Name: zhdan-utils
Version: 0.0.1.8
Summary: Utils include:
Author-email: artur.v.zhdan@gmail.com
